setup.py
qcloud_video/__init__.py
qcloud_video/auth.py
qcloud_video/conf.py
qcloud_video/video.py
qcloud_video.egg-info/PKG-INFO
qcloud_video.egg-info/SOURCES.txt
qcloud_video.egg-info/dependency_links.txt
qcloud_video.egg-info/requires.txt
qcloud_video.egg-info/top_level.txt