Metadata-Version: 1.0
Name: qcloud-video
Version: 1.0.1
Summary: python sdk for app.qcloud.com
Home-page: UNKNOWN
Author: jayli
Author-email: jayli@tencent.com
License: MIT License
Keywords: tencentyun,qcloud,video
Platform: any
